mapping_agent/__init__.py
mapping_agent/agent.py
mapping_agent/config.py
mapping_agent/constants.py
mapping_agent/models.py
mapping_agent/utils.py
mapping_agent-0.1.1.dist-info/METADATA
mapping_agent-0.1.1.dist-info/WHEEL
mapping_agent-0.1.1.dist-info/entry_points.txt
mapping_agent-0.1.1.dist-info/top_level.txt
mapping_agent-0.1.1.dist-info/RECORD
