Metadata-Version: 2.4
Name: mapping-agent
Version: 0.1.1
Summary: LLM-driven agent for creating detailed column-to-attribute mappings
Author-email: StepFn AI <rajesh@stepfunction.ai>
License-Expression: MIT
Project-URL: Homepage, https://github.com/stepfnAI/mapping-agent
Project-URL: Repository, https://github.com/stepfnAI/mapping-agent
Project-URL: Issues, https://github.com/stepfnAI/mapping-agent/issues
Classifier: Development Status :: 3 - Alpha
Classifier: Intended Audience :: Developers
Classifier: Programming Language :: Python :: 3
Classifier: Programming Language :: Python :: 3.9
Classifier: Programming Language :: Python :: 3.10
Classifier: Programming Language :: Python :: 3.11
Requires-Python: >=3.10
Requires-Dist: sfn-blueprint>=0.6.6
Requires-Dist: pandas>=2.0.0
Requires-Dist: numpy>=1.24.0
Requires-Dist: openpyxl>=3.1.0
Requires-Dist: pyarrow>=12.0.0
Provides-Extra: dev
Requires-Dist: pytest>=7.0.0; extra == "dev"
Requires-Dist: pytest-cov>=4.0.0; extra == "dev"
Requires-Dist: black>=23.0.0; extra == "dev"
Requires-Dist: flake8>=6.0.0; extra == "dev"
Requires-Dist: mypy>=1.0.0; extra == "dev"
